{
    "id": "6e00243f-eacc-4bd1-85bf-ff39375c9f0f",
    "index": 203248,
    "dir_index": 248,
    "date": "2023-11-10",
    "title": "Хадис 248",
    "body": "\u003cp\u003eحَدَّثَنَا عَبْدُ اللَّهِ بْنُ يُوسُفَ، أَخْبَرَنَا مَالِكٌ، عَنْ عَبْدِ اللَّهِ بْنِ أَبِي بَكْرٍ، عَنْ عَبَّادِ بْنِ تَمِيمٍ أَنَّ أَبَا بَشِيرٍ الْأَنْصَارِيَّ رَضِيَ اللَّهُ عَنْهُ، أَخْبَرَهُ أَنَّهُ كَانَ مَعَ رَسُولِ اللَّهِ صَلَّى اللَّهُ عَلَيْهِ وَسَلَّمَ فِي بَعْضِ أَسْفَارِهِ، قَالَ عَبْدُ اللَّهِ: حَسِبْتُ أَنَّهُ، قَالَ: وَالنَّاسُ فِي مَبِيتِهِمْ، فَأَرْسَلَ رَسُولُ اللَّهِ صَلَّى اللَّهُ عَلَيْهِ وَسَلَّمَ رَسُولًا\" أَنْ لَا يَبْقَيَنَّ فِي رَقَبَةِ بَعِيرٍ قِلَادَةٌ مِنْ وَتَرٍ أَوْ قِلَادَةٌ إِلَّا قُطِعَتْ\".\u003cbr /\u003e\n[صحیح البخاري:3005، صحیح مسلم:2115]\u003cbr /\u003e\n\u003cbr /\u003e\nПередал АбдуЛлах ибн Юсуф, которому передал Малик от АбдуЛлаха ибн Абу Бакра, передавшего от Аббáда ибн Тамúма, что Башúр аль-Ансарийю, пусть будет доволен им Аллах, ему рассказал, \u003cem\u003eчто он несколько раз был вместе с посланником Аллаха ﷺ в путешествии.\u003cbr /\u003e\n\u003c/em\u003eАбдуЛлах ибн Абу Бакр, передавший этот хадис, сказал: \u003cem\u003e«Думаю, он сказал «люди собрались в палатке / шатре, и пророк послал человека сказать, чтобы сняли с шей животных амулеты».\u003cbr /\u003e\n\u003c/em\u003e\u003cbr /\u003e\n(Аль-Бухари 3005, Муслим 2115).\u003c/p\u003e\n",
    "references": [
        "/islam_kamil/part_3/chapter_2/229"
    ],
    "meta": {
        "source": {
            "ru": [
                "Сахих Аль-Бухари 3005",
                "Сахих Муслим 2115"
            ]
        }
    }
}
