{
    "id": "9b1740ce-0255-49cf-ab9e-7122748c7287",
    "index": 203084,
    "dir_index": 84,
    "date": "2022-02-21",
    "title": "Хадис 84",
    "body": "\u003cp\u003eوحَدَّثَنَا عَبْدُ اللَّهِ بْنُ مُحَمَّدٍ، حَدَّثَنَا عَبْدُ الرَّزَّاقِ، أَخْبَرَنَا مَعْمَرٌ، عَنْ هَمَّامٍ، عَنْ أَبِي هُرَيْرَةَ، عَنِ النَّبِيِّ صَلَّى اللَّهُ عَلَيْهِ وَسَلَّمَ، قَالَ:\" رَأَى عِيسَى ابْنُ مَرْيَمَ رَجُلًا يَسْرِقُ، فَقَالَ لَهُ: أَسَرَقْتَ، قَالَ: كَلَّا وَاللَّهِ الَّذِي لَا إِلَهَ إِلَّا هُوَ، فَقَالَ عِيسَى: آمَنْتُ بِاللَّهِ وَكَذَّبْتُ عَيْنِي\".\u003cbr /\u003e\n[صحیح البخاري:3444، صحیح مسلم:2368 ]\u003cbr /\u003e\n\u003cbr /\u003e\nПередал АбдуЛлах ибн Мухаммад, ему передал Абду-Раззак, которому передал Маъмар, от Ґаммама, от Абу Хурайры, что пророк, благословение ему и благо от Аллаха, рассказал:\u003cbr /\u003e\n\u003cstrong\u003e«Увидел Иса, сын Марьям, человека, который ворует, и сказал ему:\u003cbr /\u003e\n— Ты что, воруешь?\u003cbr /\u003e\nТот ответил:\u003cbr /\u003e\n— Нет же, клянусь Аллахом! кроме которого нет достойного поклонения!\u003cbr /\u003e\nТогда Иса сказал:\u003cbr /\u003e\n— Я верю в Аллаха, а глаза мои — лгут…»\u003cbr /\u003e\n\u003c/strong\u003e\u003cbr /\u003e\n(Аль-Бухари 3444, Муслим 2368).\u003c/p\u003e\n",
    "references": [
        "/islam_kamil/part_4/chapter_2/101"
    ],
    "meta": {
        "source": {
            "ru": [
                "Сахих Аль-Бухари 3444",
                "Сахих Муслим 2368"
            ]
        }
    }
}
