{
    "id": "e4bc9f36-a7e0-4eee-ac6d-8122083c7942",
    "index": 101109,
    "dir_index": 109,
    "date": "2020-12-11",
    "title": "Права Аллаха над человеком",
    "body": "\u003cp\u003e\u003cstrong\u003eМы изучали, что для того, чтобы получить довольство и любовь\nАллаха عزَّ و جلَّ нужно следовать за Откровением, в первую очередь, нужно\nразум подчинить Откровению.\u003c/strong\u003e\u003c/p\u003e\n\u003cp\u003eАллах عزَّ و جلَّ ниспослал Откровение и это является религией, и только\nчерез религию мы можем получить довольство и любовь Аллаха عزَّ و جلَّ.\u003c/p\u003e\n\u003cp\u003e\u003cstrong\u003eЧто нам объясняет Откровение и какой является цель\nрелигии?\u003c/strong\u003e\u003c/p\u003e\n\u003cp\u003e\u003cstrong\u003eЦель Откровения - это, чтобы мы выполнили права Аллаха عزَّ و\nجلَّ и права махлюков.\u003c/strong\u003e\u003c/p\u003e\n\u003cp\u003eНа вопрос: какие же права у Аллаха عزَّ و جلَّ, может ответить только\nУахийю, то есть, Откровение.\u003c/p\u003e\n\u003cp\u003eОткровение нам объясняет, что права Аллаха عزَّ و جلَّ на человека и это,\nчтобы человек поклонялся Аллаху عزَّ و جلَّ, поклонялся только رَبِّ ٱلْعَـٰلَمِينَ,\nтолько Господу поклонялся, что только Он достоин поклонения и эти права\nне являются чьими-то правами, кроме Него.\u003c/p\u003e\n\u003cp\u003eХадис № 35 объясняет нам права Аллаха عزَّ و جلَّ.\u003c/p\u003e\n\u003cblockquote\u003e\n\u003cp\u003e\u003cstrong\u003eХадис № 35\u003c/strong\u003e\u003c/p\u003e\n\u003cblockquote\u003e\n\u003cp\u003eحَدَّثَنِي إِسْحَاقُ بْنُ إِبْرَاهِيمَ، سَمِعَ يَحْيَى بْنَ آدَمَ، حَدَّثَنَا أَبُو الأَحْوَصِ، عَنْ أَبِي\nإِسْحَاقَ، عَنْ عَمْرِو بْنِ مَيْمُونٍ، عَنْ مُعَاذٍ رَضِيَ اللَّهُ عَنْهُ، قَالَ: كُنْتُ رِدْفَ النَّبِيِّ صَلَّى\nاللهُ عَلَيْهِ وَسَلَّمَ عَلَى حِمَارٍ يُقَالُ لَهُ عُفَيْرٌ، فَقَالَ: «يَا مُعَاذُ، هَلْ تَدْرِي حَقَّ اللَّهِ\nعَلَى عِبَادِهِ، وَمَا حَقُّ العِبَادِ عَلَى اللَّهِ؟»، قُلْتُ: اللَّهُ وَرَسُولُهُ أَعْلَمُ، قَالَ: «فَإِنَّ حَقَّ\nاللَّهِ عَلَى العِبَادِ أَنْ يَعْبُدُوهُ وَلاَ يُشْرِكُوا بِهِ شَيْئًا، وَحَقَّ العِبَادِ عَلَى اللَّهِ أَنْ لاَ\nيُعَذِّبَ مَنْ لاَ يُشْرِكُ بِهِ شَيْئًا»، فَقُلْتُ: يَا رَسُولَ اللَّهِ أَفَلاَ أُبَشِّرُ بِهِ النَّاسَ؟ قَالَ:\n«لاَ تُبَشِّرْهُمْ، فَيَتَّكِلُوا»\u003c/p\u003e\n\u003ch6\nid=\"صحيح-البخاري-2856-صحيح-مسلم-30-جامع-الترمذي-2643-مسند-أحمد-22006-سنن-ابن-ماجه-4296\"\u003eصحيح\nالبخاري 2856; صحيح مسلم 30; جامع الترمذي 2643; مسند أحمد 22006; سنن ابن\nماجه 4296\u003c/h6\u003e\n\u003c/blockquote\u003e\n\u003cp\u003eИмам Аль-Бухари говорит:\u003c/p\u003e\n\u003cp\u003eПередает Исхак ибн Ибрахим, он услышал от Яхья ибн Адама, передает\nАбу аль-Ахуас, от Аби Исхака, от Амр ибн Маймун, от Муаза رضي الله\nعنه.\u003c/p\u003e\n\u003ctable\u003e\n\u003ctbody\u003e\n\u003ctr class=\"odd\"\u003e\n\u003ctd style=\"text-align: right;\"\u003eقَالَ: كُنْتُ رِدْفَ النَّبِيِّ صَلَّى اللهُ عَلَيْهِ وَسَلَّمَ عَلَى\nحِمَارٍ\u003c/td\u003e\n\u003ctd style=\"text-align: left;\"\u003eМуаз رضي الله عنه говорит, что как-то он\nсидел позади пророка صلى الله عليه وسلم на осле.\u003c/td\u003e\n\u003c/tr\u003e\n\u003ctr class=\"even\"\u003e\n\u003ctd style=\"text-align: right;\"\u003eيُقَالُ لَهُ عُفَيْرٌ\u003c/td\u003e\n\u003ctd style=\"text-align: left;\"\u003eи его (осла) звали Ъуфайр.\u003c/td\u003e\n\u003c/tr\u003e\n\u003ctr class=\"odd\"\u003e\n\u003ctd style=\"text-align: right;\"\u003eفَقَالَ:\u003c/td\u003e\n\u003ctd style=\"text-align: left;\"\u003eпосланник Аллаха صلى الله عليه وسلم\nсказал:\u003c/td\u003e\n\u003c/tr\u003e\n\u003ctr class=\"even\"\u003e\n\u003ctd style=\"text-align: right;\"\u003eيَا مُعَاذُ\u003c/td\u003e\n\u003ctd style=\"text-align: left;\"\u003eо, Муаз!\u003c/td\u003e\n\u003c/tr\u003e\n\u003ctr class=\"odd\"\u003e\n\u003ctd style=\"text-align: right;\"\u003eهَلْ تَدْرِي حَقَّ اللَّهِ عَلَى عِبَادِهِ،\u003c/td\u003e\n\u003ctd style=\"text-align: left;\"\u003eТы знаешь права Аллаха عزَّ و جلَّ на\nлюдей?\u003c/td\u003e\n\u003c/tr\u003e\n\u003ctr class=\"even\"\u003e\n\u003ctd style=\"text-align: right;\"\u003eوَمَا حَقُّ العِبَادِ عَلَى اللَّهِ؟\u003c/td\u003e\n\u003ctd style=\"text-align: left;\"\u003eи права людей на Аллаха عزَّ و جلَّ?\u003c/td\u003e\n\u003c/tr\u003e\n\u003ctr class=\"odd\"\u003e\n\u003ctd style=\"text-align: right;\"\u003eقُلْتُ: اللَّهُ وَرَسُولُهُ أَعْلَمُ\u003c/td\u003e\n\u003ctd style=\"text-align: left;\"\u003eЯ сказал: «Аллах عزَّ و جلَّ и Его посланник\nлучше знают».\u003c/td\u003e\n\u003c/tr\u003e\n\u003ctr class=\"even\"\u003e\n\u003ctd style=\"text-align: right;\"\u003eقَالَ:\u003c/td\u003e\n\u003ctd style=\"text-align: left;\"\u003eПосланник Аллаха صلى الله عليه وسلم\nсказал:\u003c/td\u003e\n\u003c/tr\u003e\n\u003ctr class=\"odd\"\u003e\n\u003ctd style=\"text-align: right;\"\u003eفَإِنَّ حَقَّ اللَّهِ عَلَى العِبَادِ\u003c/td\u003e\n\u003ctd style=\"text-align: left;\"\u003eПоистине права Аллаха عزَّ و جلَّ на\nлюдей,\u003c/td\u003e\n\u003c/tr\u003e\n\u003ctr class=\"even\"\u003e\n\u003ctd style=\"text-align: right;\"\u003eأَنْ يَعْبُدُوهُ\u003c/td\u003e\n\u003ctd style=\"text-align: left;\"\u003eчтобы люди Ему поклонялись,\u003c/td\u003e\n\u003c/tr\u003e\n\u003ctr class=\"odd\"\u003e\n\u003ctd style=\"text-align: right;\"\u003eوَلاَ يُشْرِكُوا بِهِ شَيْئًا\u003c/td\u003e\n\u003ctd style=\"text-align: left;\"\u003eи ширк не совершали, вообще.\u003c/td\u003e\n\u003c/tr\u003e\n\u003ctr class=\"even\"\u003e\n\u003ctd style=\"text-align: right;\"\u003eوَحَقَّ العِبَادِ عَلَى اللَّهِ\u003c/td\u003e\n\u003ctd style=\"text-align: left;\"\u003eИ права людей на Аллаха عزَّ و جلَّ,\u003c/td\u003e\n\u003c/tr\u003e\n\u003ctr class=\"odd\"\u003e\n\u003ctd style=\"text-align: right;\"\u003eأَنْ لاَ يُعَذِّبَ\u003c/td\u003e\n\u003ctd style=\"text-align: left;\"\u003eчтобы Аллах عزَّ و جلَّ عزّ وجلّ не\nнаказывал,\u003c/td\u003e\n\u003c/tr\u003e\n\u003ctr class=\"even\"\u003e\n\u003ctd style=\"text-align: right;\"\u003eمَنْ لاَ يُشْرِكُ بِهِ شَيْئًا\u003c/td\u003e\n\u003ctd style=\"text-align: left;\"\u003eкто, вообще ширк не совершает.\u003c/td\u003e\n\u003c/tr\u003e\n\u003ctr class=\"odd\"\u003e\n\u003ctd style=\"text-align: right;\"\u003eفَقُلْتُ: يَا رَسُولَ اللَّهِ\u003c/td\u003e\n\u003ctd style=\"text-align: left;\"\u003eЯ сказал: «О, посланник Аллаха.\u003c/td\u003e\n\u003c/tr\u003e\n\u003ctr class=\"even\"\u003e\n\u003ctd style=\"text-align: right;\"\u003eأَفَلاَ أُبَشِّرُ بِهِ النَّاسَ؟\u003c/td\u003e\n\u003ctd style=\"text-align: left;\"\u003eМожно я этим обрадую людей?\u003c/td\u003e\n\u003c/tr\u003e\n\u003ctr class=\"odd\"\u003e\n\u003ctd style=\"text-align: right;\"\u003eقَالَ:\u003c/td\u003e\n\u003ctd style=\"text-align: left;\"\u003eПосланник Аллаха صلى الله عليه وسلم\nсказал:\u003c/td\u003e\n\u003c/tr\u003e\n\u003ctr class=\"even\"\u003e\n\u003ctd style=\"text-align: right;\"\u003eلاَ تُبَشِّرْهُمْ\u003c/td\u003e\n\u003ctd style=\"text-align: left;\"\u003eНе обрадуй их (то есть, не говори им\nэто)\u003c/td\u003e\n\u003c/tr\u003e\n\u003ctr class=\"odd\"\u003e\n\u003ctd style=\"text-align: right;\"\u003eفَيَتَّكِلُوا\u003c/td\u003e\n\u003ctd style=\"text-align: left;\"\u003eиначе они перестанут дела совершать».\u003c/td\u003e\n\u003c/tr\u003e\n\u003c/tbody\u003e\n\u003c/table\u003e\n\u003c/blockquote\u003e\n\u003cp\u003e\u003cstrong\u003eАш-Шарха\u003c/strong\u003e\u003c/p\u003e\n\u003cp\u003eعَنْ مُعَاذٍ رَضِيَ اللَّهُ عَنْهُ -\u003c/p\u003e\n\u003cp\u003eМуаз — это сподвижник. Надо говорить مُعَاذُ «Муаз», а не مَعَاذٌ «Мааз»,\nпотому что مَعَاذٌ — это спаситель, и это качество Аллаха عزّ وجلّ.\u003c/p\u003e\n\u003cp\u003eقَالَ: — сказал.\u003c/p\u003e\n\u003cp\u003eكُنْتُ — был я, رِدْفَ\u003c/p\u003e\n\u003cp\u003eВ одном риваяте رَدِيفَ\u003c/p\u003e\n\u003cp\u003eВ обоих хадисах одинаковый смысл.\u003c/p\u003e\n\u003cp\u003eЕго асль رَدِيفَ — быть позади, رادف.\u003c/p\u003e\n\u003cp\u003eНапример, тот, кто сидит на мотоцикле сзади, то он является رَادِف и\nرَديف.\u003c/p\u003e\n\u003cp\u003eالنَّبِيِّ صَلَّى اللهُ عَلَيْهِ وَسَلَّمَ — То есть, позади пророка صلى الله عليه وسلم\n сидел.\u003c/p\u003e\n\u003cp\u003eعَلَى — на, حِمَارٍ — осле.\u003c/p\u003e\n\u003cp\u003eيُقَالُ لَهُ — назвали его, عُفَيْرٌ — Ъуфайр.\u003c/p\u003e\n\u003cp\u003eТакая привычка была у пророка صلى الله عليه وسلم  животным давать\nклички.\u003c/p\u003e\n\u003cp\u003eИ дальше мы, إنْ شَآءَ اللهُ будем изучать, что в хадисах есть много\nтакого, которые доказаны из хадисов, но не является Сунной.\u003c/p\u003e\n\u003cp\u003eНапример, давать клички животным не является Сунной, одевать عِمَامَةٌ\n(чалма) не является Сунной.\u003c/p\u003e\n\u003cp\u003eТакже, например в этом хадисе сказано, что посланник Аллаха صلى الله\nعليه وسلم  путешествовал на верховом животном, на осле, но это не Сунна,\nа это было соответственно того времени.\u003c/p\u003e\n\u003cp\u003eИ это мирской момент, это не религия, поэтому, если кто-то катается\nна осле, или называет своего осла «Ъуфайр» и так далее, просто из-за\nлюбви к пророку صلى الله عليه وسلم , то может получить награду за любовь\nк пророку صلى الله عليه وسلم . Но это ни в коем случае не является\nрелигией и это нельзя называть Сунной.\u003c/p\u003e\n\u003cp\u003eفَقَالَ: — Посланник Аллаха صلى الله عليه وسلم  говорит:\u003c/p\u003e\n\u003cp\u003e«يَا مُعَاذُ، هَلْ تَدْرِي — о Муаз,\u003c/p\u003e\n\u003cp\u003eهَلْ — это вопрос.\u003c/p\u003e\n\u003cp\u003eتَدْرِي — ты знаешь\u003c/p\u003e\n\u003cp\u003eحَقَّ اللَّهِ — права Аллаха?\u003c/p\u003e\n\u003cp\u003eحَقَّ — это обязательная вещь, которую ты должен кому-то дать.\u003c/p\u003e\n\u003cp\u003eعَلَى عِبَادِهِ — на людей.\u003c/p\u003e\n\u003cp\u003eعِبَادٌ — это множественное число, عَبْدٌ — единственное число.\u003c/p\u003e\n\u003cp\u003eوَمَا حَقُّ العِبَادِ — и какие права у людей\u003c/p\u003e\n\u003cp\u003eعَلَى اللَّهِ؟» — на Аллаха?\u003c/p\u003e\n\u003cp\u003eقُلْتُ: — Я сказал:\u003c/p\u003e\n\u003cp\u003eاللَّهُ وَرَسُولُهُ أَعْلَمُ — Аллах и Его посланник лучше знают. أَعْلَمُ - это\n«лучше».\u003c/p\u003e\n\u003cp\u003eМы говорим: يعْلَمُ - знает, أَعْلَمُ - более знающий, то есть лучше\nзнает.\u003c/p\u003e\n\u003cp\u003eЕсли мы скажем: الله يعلم - Аллах عزَّ و جلَّ знает. А мы говорим: الله\nأَعْلَمُ - Аллах عزَّ و جلَّ больше знает.\u003c/p\u003e\n\u003cp\u003eفَإِنَّ حَقَّ اللَّهِ — Поистине, права Аллаха\u003c/p\u003e\n\u003cp\u003eعَلَى العِبَادِ — на людей,\u003c/p\u003e\n\u003cp\u003eأَنْ يَعْبُدُوهُ — чтобы люди Ему поклонялись.\u003c/p\u003e\n\u003cp\u003eعِبَادَةٌ совершали поклонение.\u003c/p\u003e\n\u003cp\u003eوَلاَ يُشْرِكُوا بِهِ شَيْئًا — и شَرِيكٌ шарик не делали с Аллахом, вообще.\u003c/p\u003e\n\u003cp\u003eوَحَقَّ العِبَادِ عَلَى اللَّهِ — и права людей на Аллаха,\u003c/p\u003e\n\u003cp\u003eأَنْ لاَ يُعَذِّبَ — чтобы Аллах не делал\u003c/p\u003e\n\u003cp\u003eعَذَابٌ - мучения, наказание\u003c/p\u003e\n\u003cp\u003eمَنْ — кто, لاَ يُشْرِكُ بِهِ شَيْئًا — не делает شَرِيكٌ с Аллахом عزَّ و جلَّ شَيْئًا -\nвообще.\u003c/p\u003e\n\u003cp\u003eВ риваяте «Муснад» Ахмада есть дополнительное предложение:\u003c/p\u003e\n\u003cp\u003e\"فَإِنَّ حَقَّ الْعِبَادِ عَلَى اللهِ إِذَا فَعَلُوا ذَلِكَ أَنْ يُدْخِلَهُمُ الْجَنَّةَ\"\u003c/p\u003e\n\u003cp\u003eفَإِنَّ حَقَّ الْعِبَادِ عَلَى اللهِ — Поистине, права людей на Аллаха عزَّ و جلَّ,\u003c/p\u003e\n\u003cp\u003eإِذَا فَعَلُوا ذَلِكَ — когда они это делают (то есть, соблюдают таухид, не\nделают ширк),\u003c/p\u003e\n\u003cp\u003eأَنْ يُدْخِلَهُمُ الْجَنَّةَ — чтобы ввести их в Рай.\u003c/p\u003e\n\u003cp\u003eТо есть, права людей на Аллаха عزَّ و جلَّ, что Он введет их в Рай.\u003c/p\u003e\n\u003cp\u003eЭто одно и то же.\u003c/p\u003e\n\u003cp\u003eМы говорили, что в хадисе главное – это смысл, цель и суть.\u003c/p\u003e\n\u003cp\u003eНапример, когда человек не совершает ширк, то он попадает в Рай.\nПопасть в Рай - это и есть не получить мучения и не попасть в Ад. Права\nлюдей на Аллаха عزَّ و جلَّ - это то, чтобы Аллах عزَّ و جلَّ не наказывал\nих.\u003c/p\u003e\n\u003cp\u003eВ другом риваяте говорится, что Аллах عزَّ و جلَّ введет их в Рай, то\nесть, это получается одно и то же. Хадисы передаются разными словами, а\nсуть одна и та же.\u003c/p\u003e\n\u003cp\u003eПоэтому, в хадисах бывают разные слова и это не является целью.\nГлавное это, чтобы человек понял смысл хадиса. Риваяты могут быть\nразные, сподвижник мог передать своими словами, после сподвижников\nдругие люди могли передать своими словами, но главное - суть. Когда мы\nсобираем разные риваяты, то общая суть - это урок хадиса.\u003c/p\u003e\n\u003cp\u003eИ мы постоянно говорим, что Куръан отличается от хадиса тем, что\nКуръан пришел и слова и смысл его сохранились. Хадисы тоже пришли от\nАллаха عزَّ و جلَّ, но слова там разные. Самое главное, что там смысл и суть\nсохранились. А то, что разными словами нам передаются, то в этом тоже\nесть очень большое благо.\u003c/p\u003e\n\u003cp\u003eНапример, в одном риваяте говорится, что Аллах عزَّ و جلَّ не наказывает\nих. А что значит «не наказывает»?\u003c/p\u003e\n\u003cp\u003eВ другом риваяте говорится, что Аллах عزَّ و جلَّ введет их в Рай,\nзначит, не наказывал в Аду. Один риваят является шархом (объяснением)\nдля другого риваята.\u003c/p\u003e\n\u003cp\u003eВ этом риваяте объясняется ответ на очень важный вопрос.\u003c/p\u003e\n\u003cp\u003e\u003cstrong\u003eВопрос такой, что в этом хадисе сказано, что если человек не\nделает ширк, то его права, чтобы Аллах عزَّ و جلَّ его не наказал. Значит,\nесли человек не совершал ширк, то он никогда не попадает в Ад, то есть,\nчеловек ширк не совершал, но совершал другие грехи и, значит, он не\nпопадает в Ад?\u003c/strong\u003e\u003c/p\u003e\n\u003cp\u003e\u003cstrong\u003eОтвет на этот вопрос: Здесь, когда говорится о том, что не\nнакажет, это имеется в виду, что вечно не наказывает, то есть, он в Рай\nпопадет.\u003c/strong\u003e\u003c/p\u003e\n\u003cp\u003eЕсли человек в жизни совершал много грехов и Аллах عزَّ و جلَّ его не\nпростил, и он является муваххид (тот, кто соблюдает таухид и не делает\nширк), то такой человек сначала попадает в Ад, и потом попадет в\nРай.\u003c/p\u003e\n\u003cp\u003eЗдесь говорится, что Аллах عزَّ و جلَّ его не накажет, то есть, Аллах عزَّ\nو جلَّ его обязательно потом введет в Рай. Не накажет - имеется в виду,\nвечно не будет наказывать. Потому что другие аяты и другие хадисы нам\nнужно объединять, так как есть другие хадисы, где говорится, что за\nгрехи будет наказание, за свои грехи человеку будет наказание. Но здесь\nимеется в виду, что Аллах عزَّ و جلَّ не накажет его вечно в Аду, не накажет\nтак, как мушрика накажет вечно в Аду.\u003c/p\u003e\n\u003cp\u003eПолучается, если для мушрика будет вечный Ад, то для муваххида\nвечного Ада не будет, и если он совершал грехи, то очистится в Аду и\nзатем зайдет в Рай.\u003c/p\u003e\n\u003cp\u003eДальше в этом хадисе говорится:\u003c/p\u003e\n\u003cp\u003e فَقُلْتُ - я сказал يَا رَسُولَ اللَّهِ – о, посланник Аллаха صلى الله عليه\nوسلم\u003c/p\u003e\n\u003cp\u003e أَفَلاَ أُبَشِّرُ - можно я сообщу ( أُبَشِّرُ - это от слово أُبَشِّر-\nобрадовать).\u003c/p\u003e\n\u003cp\u003e بِهِ - этой вестью, которой ты сказал,\u003c/p\u003e\n\u003cp\u003e النَّاسَ؟ - людей.\u003c/p\u003e\n\u003cp\u003e قَالَ: «لاَ تُبَشِّرْهُمْ - посланник Аллаха صلى الله عليه وسلم  сказал: «не\nобрадывай их»,\u003c/p\u003e\n\u003cp\u003e فَيَتَّكِلُوا - فَيَتَّكِلُوا от слова تِكَال, дословно переводится «уповать»\n(бросать дела).\u003c/p\u003e\n\u003cp\u003eТо есть, это значит, что они бросят дела и скажут: «всё равно у нас\nтаухид есть, и Аллах عزَّ و جلَّ عَزَّ وَجَلَّ нас не накажет», и поэтому они\nбросят дела, не будут читать намаз, и ничего не будут делать. Это\nзначит: оставят дела и будут опираться на то, что Аллах عزَّ و جلَّ сказал,\nчто не накажет, если не будут делать ширк.\u003c/p\u003e\n\u003cp\u003eВ хадисе «Сахих» Аль-Бухари 1362, как раз это слово:\u003c/p\u003e\n\u003cp\u003eКогда посланник Аллаха صلى الله عليه وسلم  объяснил,\u003c/p\u003e\n\u003cp\u003e فَقَالَ رَجُلٌ - то один человек сказал:\u003c/p\u003e\n\u003cp\u003eفَقَالَ رَجُلٌ يَا رَسُولَ اللَّهِ، أَفَلاَ نَتَّكِلُ عَلَى كِتَابِنَا وَنَدَعُ الْعَمَلَ – о, посланник\nАллаха, можно ли нам опираться на свой такдир, на свой кадр и оставить\nдела.\u003c/p\u003e\n\u003cp\u003eأَفَلاَ نَتَّكِلُ نَتَّكِلُ - это значит, оставить дела и опираться на какой-то\nхадис, и сказать, что есть хадис, в котором говорится, что муваххидам не\nбудет наказания, значит, им дела не нужны.\u003c/p\u003e\n\u003cp\u003eХадис «Сахих» Аль-Бухари, 5967\u003c/p\u003e\n\u003cp\u003eЭтот хадис повторяет и говорит:\u003c/p\u003e\n\u003cp\u003e ‏«‏ يَا مُعَاذُ ‏» ‏.‏ قُلْتُ لَبَّيْكَ رَسُولَ اللَّهِ وَسَعْدَيْكَ‏.‏ ثُمَّ سَارَ سَاعَةً ثُمَّ قَالَ ‏«‏ يَا\nمُعَاذُ ‏» - три раза посланник Аллаха صلى الله عليه وسلم  спрашивает\u003c/p\u003e\n\u003cp\u003e‏‏ - قُلْتُ لَبَّيْكَ رَسُولَ اللَّهِ وَسَعْدَيْكَ и Му’аз رضي الله عنه отвечает: я здесь,\nо посланник Аллаха عزَّ و جلَّ, слушаюсь тебя и подчиняюсь, и счастлив, что\nя здесь с тобой\u003c/p\u003e\n\u003cp\u003e لَبَّيْكَ رَسُولَا للَّهِ وَسَعْدَيْكَ‏ (Му’аз رضي الله عنه три раза сказал).\u003c/p\u003e\n\u003cp\u003eХадис «Сахих» Аль-Бухари, «Сахих» Муслим приводят такие слова:\u003c/p\u003e\n\u003cp\u003eمَا مِنْ أَحَدٍ - любой кто\u003c/p\u003e\n\u003cp\u003eيَشْهَدُ أَنْ لاَ إِلَهَ إِلاَّ اللَّهُ - свидетельствует, что нет иляха, кроме\nАллаха\u003c/p\u003e\n\u003cp\u003eوَأَنَّ مُحَمَّدًا رَسُولُ اللَّهِ - и что Мухаммад صلى الله عليه وسلم  - посланник\nАллаха\u003c/p\u003e\n\u003cp\u003e صِدْقًا مِنْ قَلْبِهِ - от чистого сердца\u003c/p\u003e\n\u003cp\u003e(صِدْقًا - это значит «чисто, искренне», с правдой, нет лицемерия).\u003c/p\u003e\n\u003cp\u003e مِنْ قَلْبِهِ - от всего сердца\u003c/p\u003e\n\u003cp\u003eإِلاَّ حَرَّمَهُ اللَّهُ عَلَى النَّارِ - Аллах запретил для него огонь.\u003c/p\u003e\n\u003cp\u003e«Запретил» - это значит: запретил вечный огонь, вечно он не будет в\nогне.\u003c/p\u003e\n\u003cp\u003eВторой смысл такой, что когда человек совершает куфр, ширк, а потом\nскажет «لاَ إِلَهَ إِلاَّ اللَّه», примет Ислам и сразу умрёт, то он попадает в\nРай, в Ад, вообще, не попадёт, потому что, он сразу умер.\u003c/p\u003e\n\u003cp\u003e لاَ إِلَهَ إِلاَّ اللَّهُ - нет маъбуда (مَعْبُودٌ - объекта поклонения), кроме\nАллаха عزَّ و جلَّ.\u003c/p\u003e\n\u003cp\u003eЕсли لاَ إِلَهَ - это нафи, إِلاَّ اللَّهُ - это исбат.\u003c/p\u003e\n\u003cp\u003eПервая часть - это отрицать куфр, а последняя часть - это\nподтверждать иман.\u003c/p\u003e\n\u003cp\u003eОбязательно, чтобы человек отрекся, отрицал, потому что لاَ إِلَهَ - это\nотрицание, то есть, чтобы человек отрицал, что ни идолам, ни тагуту, ни\nмогилам, никому и ничему, которым люди поклоняются, человек этому не\nбудет поклоняться.\u003c/p\u003e\n\u003cp\u003e وَأَنَّ مُحَمَّدًا رَسُولُ اللَّهِ - и что Мухаммад - посланник Аллаха صلى الله\nعليه وسلم .\u003c/p\u003e\n\u003cp\u003eДля одного индивидуала и для всего общества, очень важно, для того,\nчтобы исправиться, нужно иметь две вещи: первое: искреннее намерение; а\nвторое: совершать дела по методу пророка صلى الله عليه وسلم .\u003c/p\u003e\n\u003cp\u003eИ какой-то человек или какое-то общество, никогда не попадёт в\nзаблуждение, если у них будут эти две вещи. И они не никогда исправятся,\nпока этих двух вещей у них не будет. И они никогда не заблудятся, если у\nних будут эти две вещи.\u003c/p\u003e\n\u003cp\u003e\u003cstrong\u003eЭто основное правило: исправить намерение и исправить\nдела.\u003c/strong\u003e\u003c/p\u003e\n\u003cp\u003eИслам, в первую очередь, тебе говорит:  مُحَمَّدًا رَسُولُ اللَّهِ. لاَ إِلَهَ إِلاَّ\nاللَّهُ\u003c/p\u003e\n\u003cp\u003eلاَ إِلَهَ إِلاَّ اللَّهُ - исправляет твое намерение, учит кому поклоняться,\nкакое твоё намерение. مُحَمَّدًا رَسُولُ اللَّهِ - объясняет тебе метод, по какому\nнадо поклоняться.\u003c/p\u003e\n\u003cp\u003e لاَ إِلَهَ إِلاَّ اللَّهُ - поклоняться только одному Аллаху عزَّ و جلَّ\u003c/p\u003e\n\u003cp\u003e مُحَمَّدًا رَسُولُ اللَّهِ - поклоняться по методу пророка Мухаммада صلى الله\nعليه وسلم .\u003c/p\u003e\n\u003cp\u003eИ в «Муснад» Ахмаде есть риваят, где говорится, кто сказал لا إلَهَ إلَّا\nاللَّهُ، и потом умер на этом, то есть, ширк не совершал, то он обязательно\nзайдёт в Рай.\u003c/p\u003e\n\u003cp\u003eما مِن عَبْدٍ قالَ: لا إلَهَ إلَّا اللَّهُ، ثُمَّ مَاتَ علَى ذلكَ إلَّ دَخَلَ الجَنَّةَ\u003c/p\u003e\n\u003cp\u003eНет такого, кто говорил бы: «нет другого إلَهَ, помимо Аллаха عزَّ و جلَّ »\nи не изменил бы своих убеждений до самой смерти, что он не попал бы в\nРай!\u003c/p\u003e\n\u003cp\u003e«Муснад» Ахмад 22006, хадис сахих.\u003c/p\u003e\n\u003cp\u003e\u003cstrong\u003eНекоторые люди не понимают этот вопрос.\u003c/strong\u003e\u003c/p\u003e\n\u003cp\u003eОни думают, что понятны права Аллаха عزَّ و جلَّ над людьми, но что\nзначит: права людей на Аллаха عزَّ و جلَّ? Ответ такой, что Аллах عزَّ و جلَّ\nобещал человеку, если он будет соблюдать таухид, не будет делать ширк,\nто в Рай попадёт. Вот это обещание – это и есть права.\u003c/p\u003e\n\u003cp\u003eАллах عزَّ و جلَّ обязал Сам Себя, это по Милости Аллаха عزَّ و جلَّ, что он\nговорит эти права, и это значит, что вы точно попадёте в Рай, вас не\nобманут, если вы будете соблюдать таухид.\u003c/p\u003e\n\u003cp\u003e\u003cstrong\u003eВопрос такой: почему посланник Аллаха صلى الله عليه وسلم\n запретил Му’азу رضي الله عنه обрадовать людей?\u003c/strong\u003e\u003c/p\u003e\n\u003cp\u003e\u003cstrong\u003eОтвет такой: в то время люди не знали шарха этого хадиса, и\nони могли подумать что, если есть таухид ( есть لاَ إِلَهَ إِلاَّ اللَّهُ), то\nзначит, наказания не будет, и в Ад человек не попадёт. Поэтому посланник\nАллаха عزَّ و جلَّ صلى الله عليه وسلم  сказал, чтобы он не рассказывал им\nэтот хадис.\u003c/strong\u003e\u003c/p\u003e\n\u003cp\u003eКогда они поняли шарха этого хадиса, что есть понятие «зайти в Ад\nвечно» и есть понятие «зайти временно», и здесь, про которое говорится:\nне накажет - это «вечно не накажет». А что касается общего наказания, то\nизвестно из других доводов и доказательств, что муваххида тоже\nнаказывают, но это временное наказание, чтобы очиститься, а потом зайти\nв Рай.\u003c/p\u003e\n\u003cp\u003eТо есть, когда они поняли шарха, то Му’аз رضي الله عنه этот хадис им\nрассказал.\u003c/p\u003e\n\u003cp\u003eЭтот хадис говорит о том, что те люди, которые ещё не готовы, им не\nнадо рассказывать о таких вещах, от которых них будет фитна, здесь фитна\n- это значит, что они бросят ислам.\u003c/p\u003e\n\u003cp\u003eТо есть, здесь не говорится о том, чтобы вообще не рассказывали\nислам.\u003c/p\u003e\n\u003cp\u003eЗдесь говорится о том, что нужно готовить людей к исламу, и к чему\nони будут готовы, то это нужно им рассказывать. У некоторых людей нет\nзнания, и когда они слушают некоторые хадисы, то попадают в\nзаблуждение.\u003c/p\u003e\n\u003cp\u003eПоэтому Абдуллах ибн Масъуд رضي الله عنه сказал, что надо\nрассказывать то, что они понимают.\u003c/p\u003e\n\u003cp\u003eАбдуллах ибн Масъуд رضي الله عنه сказал:\u003c/p\u003e\n\u003cp\u003eعَنْ عَبْدِ اللَّهِ بْنِ مَسْعُودٍ قَالَ:\u003c/p\u003e\n\u003cp\u003eمَا أَنْتَ بِمُحَدِّثٍ قَوْماً حَدِيثاً لَا تَبْلُغُهُ عُقُولٌ إِلَّا كَانَ لِبَعْضِهِمْ فِتْنَةً.\u003c/p\u003e\n\u003cp\u003eПередаётся от АбдуЛлаха ибн Масъуда رضي الله عنه:\u003c/p\u003e\n\u003cp\u003e«Какой бы хадис ты не рассказывал людям, обязательно он будет кому-то\n(какой-то части людей) фитной (он послужит фитной)».\u003c/p\u003e\n\u003cp\u003eКогда ты рассказываешь людям такой хадис, который они не понимают, то\nдля них (некоторых из них) он будет фитной.\u003c/p\u003e\n\u003cp\u003e«Мукаддима «Сахих» Муслима».\u003c/p\u003e\n\u003cp\u003eЗдесь надо знать, что есть понятие «тадриджь» (تَدْرِيجٌ - постепенное\nпродвижение) - постепенно рассказывать людям, чтобы они поняли.\u003c/p\u003e\n\u003cp\u003eЕсть «халал» (خَلَلٌ) - это упущение, «خَلَلٌ» харам, а «تَدْرِيجٌ»\nдозволен.\u003c/p\u003e\n\u003cp\u003eНапример, человек принимает ислам и ему говорят, что «иди домой, и\nесли твоя супруга не наденет хиджаб (покрывало не оденет) ты разведись с\nней», то он оставит ислам, потому что он ещё не готов оставить супругу.\nТакже, например, какая-то женщина принимает ислам, и ей говорят: «теперь\nвсё, твой муж для тебя харам, ты должна с ним развестись», то она бросит\nислам. Также, например, какой-то человек принимает ислам, ему говорят,\nчто надо делать нафль, дополнительное поклонение и так далее, то это\nпротив «тадриджа», не надо усложнять людям.\u003c/p\u003e\n\u003cp\u003eИли есть такие хадисы, которые касаются такдира или кафира, и если ты\nрасскажешь им эту тему, то для людей это будет очень сложно, и люди\nнеправильно поймут.\u003c/p\u003e\n\u003cp\u003eНапример, человек принял ислам, и ему говорят, что у Аллаха عزَّ و جلَّ\nесть список, кто из людей попадёт в Рай, и кто попадёт в Ад. Тогда он\nможет сказать, зачем тогда действовать, если список уже готов, и значит\nбесполезно все делать, потому что он ещё не понимает всё эти\nвопросы.\u003c/p\u003e\n\u003cp\u003eНи в коем случае это правило не говорит о том, что людям постепенно\nнадо рассказывать ислам, то есть, например, говорить человеку, который\nпринял ислам: «в этом году ты намаз читаешь, на следующий год ты держишь\nпост, а ещё через год закат и так далее», то это неправильно.\u003c/p\u003e\n\u003cp\u003eЭтот хадис, ни в коем случаи не говорит о том, что надо скрывать\nистину.\u003c/p\u003e\n\u003cp\u003eПосланник Аллаха صلى الله عليه وسلم  не запретил, чтобы людям\nрассказывали права Аллаха عزَّ و جلَّ, и права людей. А посланник Аллаха صلى\nالله عليه وسلم  сказал, что люди оставит дела, и у них есть проблемы,\nпока они не поймут, то не рассказывай.\u003c/p\u003e\n\u003cp\u003eНекоторые люди скрывают вопросы ислама, и оправдывают себя этим\nхадисом, и говорят, что если они будут всё рассказывать, то люди попадут\nв заблуждение.\u003c/p\u003e\n\u003cp\u003eЕсли так скрывать истину, то часть людей, вообще не получат знания,\nтем более, что ислам не говорит: «не рассказывайте», то есть, сначала,\nнужно людям объяснить.\u003c/p\u003e\n\u003cp\u003eДаже, если человек хочет рассказать сложный вопрос, то, сначала его\nнужно объяснить. Некоторые люди делают «истидлях», то есть, этот хадис\nберут как довод и говорят, что людям надо рассказывать только таухид и\nакыду, и всё.\u003c/p\u003e\n\u003cp\u003eЭтот хадис говорит о том, что надо не рассказывать людям только в те\nмоменты, когда люди попадут в заблуждение, и сначала им нужно объяснить,\nа потом рассказать, то есть, рассказывать обязательно.\u003c/p\u003e\n\u003cp\u003eПоэтому не правы те люди, которые запрещают рассказывать некоторые\nтемы из ислама. Должна быть объяснена каждая тема из ислама! Их надо\nрассказывать людям, но сразу не надо вдаваться в сложные темы.\u003c/p\u003e\n\u003cp\u003eСкрывать же истину – привычка иудеев.\u003c/p\u003e\n\u003cp\u003eАллах عزَّ و جلَّ в Куръане Говорит:\u003c/p\u003e\n\u003cblockquote\u003e\n\u003cblockquote\u003e\n\u003cp\u003eوَلَا تَلْبِسُوا الْحَقَّ بِالْبَاطِلِ وَتَكْتُمُوا الْحَقَّ وَأَنتُمْ تَعْلَمُونَ\u003c/p\u003e\n\u003ch6 id=\"سورة-البقرة-آية-42\"\u003eسورة البقرة، آية 42\u003c/h6\u003e\n\u003c/blockquote\u003e\n\u003cblockquote\u003e\n\u003cp\u003eИ не смешивайте истину с ложью, и не скрывайте её, когда она вам\nизвестна!\u003c/p\u003e\n\u003ch6 id=\"сура-аль-бакара-аят-42\"\u003eСура Аль-Бакара, аят 42\u003c/h6\u003e\n\u003c/blockquote\u003e\n\u003c/blockquote\u003e\n\u003cp\u003eИ это было привычкой христиан.\u003c/p\u003e\n\u003cblockquote\u003e\n\u003cblockquote\u003e\n\u003cp\u003eيَا أَهْلَ الْكِتَابِ لِمَ تَلْبِسُونَ الْحَقَّ بِالْبَاطِلِ وَتَكْتُمُونَ الْحَقَّ وَأَنتُمْ تَعْلَمُونَ\u003c/p\u003e\n\u003ch6 id=\"سورة-آل-عمران-آية-71\"\u003eسورة آل عمران, آية 71\u003c/h6\u003e\n\u003c/blockquote\u003e\n\u003cblockquote\u003e\n\u003cp\u003eО, люди Писания! Зачем вы смешиваете истину с ложью и скрываете её,\nхотя она вам известна?!\u003c/p\u003e\n\u003ch6 id=\"сура-аль-имран-аят-71\"\u003eСура Аль Имран, аят 71\u003c/h6\u003e\n\u003c/blockquote\u003e\n\u003c/blockquote\u003e\n\u003cp\u003eТо есть, если у вас есть знания, то вам нужно об этих вопросах людям\nрассказывать!\u003c/p\u003e\n\u003cp\u003eПоэтому те, которые, оправдываясь этим хадисом, говорят не\nрассказывать людям определённые темы, не правы.\u003c/p\u003e\n\u003cp\u003eИ также в достоверном хадисе сказано, что тому, кто скрывал истину,\nнаденут в Судный День на лицо намордник из Огня!..\u003c/p\u003e\n\u003cp\u003eЧто же касается нашего основного хадиса, о котором с начала урока\nидёт речь, то ведь посланник Аллаха صلى الله عليه وسلم  не запретил\nМуазу рассказывать людям таухид, объяснять религию; он только сказал,\nчтобы он не говорил только об этом достоинстве. То есть, ему нужно\nподождать, не говорить пока, людям рано было знать об этом, потому что\nони неправильно поймут.\u003c/p\u003e\n\u003cp\u003eА также посланник Аллаха صلى الله عليه وسلم  говорил, что если бы это\nне стало для людей фитной, то он бы перестроил Каабу по-другому: как ее\nпостроил Ибрахим.\u003c/p\u003e\n\u003cp\u003eЗдесь то же: это не было приказом Аллаха عزَّ و جلَّ – перестроить Каабу\n– это было просто желанием пророка صلى الله عليه وسلم, это не религия и\nне Сунна, и он пожертвовал своим желанием ради того, чтобы у людей не\nбыло фитны.\u003c/p\u003e\n\u003cp\u003eА если так понимать, что не надо рассказывать людям истины, чтобы у\nних не было фитны, тогда и таухид рассказывать, выходит, не надо\nбыло…\u003c/p\u003e\n\u003cp\u003eПосланник Аллаха صلى الله عليه وسلم  в Макке рассказывал людям\nистину, были из-за этого и войны, и сколько было людей против, сколько\nфитны случилось! Но Аллах عزَّ و جلَّ же не сказал, что раз фитна, то всё,\nничего рассказывать тогда не надо…\u003c/p\u003e\n\u003cp\u003eНе надо смотреть, есть ли фитна; фитны будут, когда истину\nрассказывают, но это не означает, что нужно остановиться и не говорить\nбольше ничего!\u003c/p\u003e\n\u003cp\u003eЭтот хадис, ни в коем случае, не говорит, что нужно оставить те\nСунны, которые людям не известны. Многие попали в заблуждение в этом\nвопросе, они говорят, чтобы «аминь» не говорили громко, руки\nдополнительно во время салята не поднимали (при переходе из кыяма в\nрукуъ и обратно и перед началом следующего ракаата) потому, что это\nбудет фитной для тех, кто к этому не привыкли… И много таких вопросов,\nкогда запрещают, говорят, что в какой местности вы живёте, так и\nсоблюдайте ту часть религии, к которой там привыкли…\u003c/p\u003e\n\u003cp\u003eЭто неправильно совсем.\u003c/p\u003e\n\u003cp\u003eВся религия была новой для людей, они её не понимали, но посланник\nАллаха صلى الله عليه وسلم  пришел и рассказал им всю религию.\nСподвижники выполняли всю Сунну, даже перед кяфирами, даже если была\nфитна – потому, что они знали, что такое фитна.\u003c/p\u003e\n\u003cp\u003eФитна – это когда получается вред для ислама, если человек из-за этой\nфитны оставит ислам!..\u003c/p\u003e\n\u003cp\u003eНапример, какой-то мустахаб, совершают дополнительное поклонение, а у\nлюдей из-за этого появляется ненависть к исламу, люди ислам оставят, то\nвот это фитна, и тогда лучше этот мустахаб (желательное действие)\nоставить. Но то, что обязательно в исламе, об этом рассказывать тоже\nобязательно! А доводом этому служит Куръан, аяты, где говорится, что не\nнужно истину скрывать.\u003c/p\u003e\n\u003cp\u003eА люди начинают говорить, что не надо с минбара объяснять, что Аллах\nعزَّ و جلَّ находится над Аршем, потому что для них это может быть фитной,\nоправдываясь этим хадисом… Неправильно. Неправильно!\u003c/p\u003e\n\u003cp\u003eЕсть достоверный хадис, в котором говорится, что «إِنَّهُ لاَ يَأْتِي الْخَيْرُ\nبِالشَّرِّ - благо беды не принесёт!» «Сахих» Аль-Бухари, 1465.\u003c/p\u003e\n\u003cp\u003eНаоборот, когда будешь рассказывать людям, то фитны не будет!\u003c/p\u003e\n\u003cp\u003eКуръан и Сунна беды и проблем не принесут!\u003c/p\u003e\n\u003cp\u003eВопрос такой возникает: если посланник Аллаха صلى الله عليه وسلم\n запретил Муазу рассказывать этот хадис, тогда почему он его\nрассказал?\u003c/p\u003e\n\u003cp\u003eНо ведь посланник Аллаха صلى الله عليه وسلم  не сказал, чтобы не\nрассказывать его никогда, а имелось в виду, что пока люди шарха не\nпонимали, то им не надо рассказывать, и когда они поняли религию, то\nобязательно надо им рассказать. И Муаз рассказал этот хадис перед\nсмертью, чтобы не было на нём греха.\u003c/p\u003e\n\u003cp\u003e«Сахих» Аль-Бухари и «Сахих» Муслим передают, что\u003c/p\u003e\n\u003cp\u003eوَأَخْبَرَ بِهَا مُعَاذٌ عِنْدَ مَوْتِهِ تَأَثُّمًا\u003c/p\u003e\n\u003cp\u003eМуаз рассказал этот хадис, когда почувствовал, что умирает, боясь\nгреха, чтобы не осталось на нём греха, чтобы истину не скрывать.\u003c/p\u003e\n\u003cp\u003e\u003cstrong\u003eПользы хадиса\u003c/strong\u003e\u003c/p\u003e\n\u003cp\u003e(فِقْهُ الحَدِيثِ - что мы поняли из этого хадиса)\u003c/p\u003e\n\u003cp\u003e\u003cstrong\u003e1.   Что поклоняться одному Аллаху عزَّ و جلَّ – это Его право\nтребовать от людей. Кто поклоняется кому-то ещё, тот нарушает права\nАллаха عزَّ و جلَّ.\u003c/strong\u003e\u003c/p\u003e\n\u003cp\u003e\u003cstrong\u003e2.   Тем, кто говорят, что изучать религию не обязательно,\nсоблюдать, другим объяснять, никакой от этого пользы нет, этот хадис\nслужит опровержением.\u003c/strong\u003e\u003c/p\u003e\n\u003cp\u003eЭти дела – это поклонение, а поклонение - это право Аллаха عزَّ و جلَّ.\nТем, что вы изучаете религию, соблюдаете её и объясняете другим, вы\nвыполняете права Аллаха عزَّ و جلَّ.\u003c/p\u003e\n\u003cp\u003e\u003cstrong\u003e3.   Дела тех людей, которые соблюдают ислам просто как\nтрадицию, не примутся Аллахом عزَّ و جلَّ. Ислам - это не традиция, ислам –\nэто права Аллаха عزَّ و جلَّ!\u003c/strong\u003e\u003c/p\u003e\n\u003cp\u003e\u003cstrong\u003e4.   Поклоняться Аллаху عزَّ و جلَّ - это фард, потому что это\nправа Аллаха عزَّ و جلَّ над человеком.\u003c/strong\u003e\u003c/p\u003e\n\u003cp\u003eЕсть люди, которые соблюдают права детей, семьи, но нарушают права\nАллаха عزَّ و جلَّ – это большая несправедливость, это зульм, а зульм - это\nкак раз нарушение прав!\u003c/p\u003e\n\u003cp\u003e\u003cstrong\u003e5.   Есть люди, которые говорят, что они много делают для\nдругих, помогают людям, например, врачи и другие, и они говорят, что за\nто, что они приносят столько пользы, то могут не читать салят и так\nдалее, то это ложное представление и это неправильно.\u003c/strong\u003e\u003c/p\u003e\n\u003cp\u003e\u003cstrong\u003eПрава Аллаха عزَّ و جلَّ надо выполнять в первую\nочередь!\u003c/strong\u003e\u003c/p\u003e\n\u003cp\u003e\u003cstrong\u003e6.   Мы поняли, что даже если человек совершит не много\nширка, то его дела аннулируются, и он нарушает права Аллаха عزَّ و جلَّ, а\nправа Аллаха عزَّ و جلَّ на нём так и остаются.\u003c/strong\u003e\u003c/p\u003e\n\u003cp\u003e\u003cstrong\u003e7.   Мы поняли, что надо знать смысл поклонения, потому что\nэто обязанность каждого, потому что это права Аллаха عزَّ و جلَّ, а их надо\nзнать.\u003c/strong\u003e\u003c/p\u003e\n\u003cp\u003e\u003cstrong\u003e8.   Мы узнали, что посланник Аллаха صلى الله عليه وسلم\nпутешествовал верхом на осле, а это говорит о его\nскромности.\u003c/strong\u003e\u003c/p\u003e\n\u003cp\u003e\u003cstrong\u003e9.   Мы поняли, что когда люди принимают ислам, то не нужно\nим сразу рассказывать такие вещи, которые им будет сложно понять, из-за\nкоторых они могут бросить ислам.\u003c/strong\u003e\u003c/p\u003e\n\u003cp\u003e\u003cstrong\u003e10.   Мы поняли, что очень важно людям совершать الْعَمَلُ амаль\n– дела, прилагать усилия.\u003c/strong\u003e\u003c/p\u003e\n\u003cp\u003eПосланник Аллаха صلى الله عليه وسلم сказал не рассказывать этот\nхадис, потому что они оставят амаль – значит, дела это очень важны! Ради\nтого, чтобы люди не оставили дела, посланник Аллаха صلى الله عليه وسلم\nсказал: не рассказывать им это достоинство, этот хадис.\u003c/p\u003e\n\u003cp\u003e\u003cstrong\u003e11.   Мы поняли, как хорошо сохраняли сподвижники хадисы\nпророка صلى الله عليه وسلم!\u003c/strong\u003e\u003c/p\u003e\n\u003cp\u003eВидите, здесь говорится даже о том, как звали этого осла – Уфайр. Как\nподробно всё это сохраняется! Аллах عزَّ و جلَّ сохраняет хадисы!\u003c/p\u003e\n\u003cp\u003e\u003cstrong\u003e12.   Мы поняли, что этот хадис служит опровержением тем, кто\nне читают салят и говорят, что намаз не обязателен и так\nдалее.\u003c/strong\u003e\u003c/p\u003e\n\u003cp\u003eЭто права Аллаха عزَّ و جلَّ! Как это не нужно?! Это очень важно. Те,\nкоторые не читают салят, нарушают права своего Создателя, и это очень\nбольшое преступление.\u003c/p\u003e\n\u003cp\u003e\u003cstrong\u003e13.   Мы поняли, что те люди, которые будут выполнять таухид\nи не будут совершать ширк, обязательно попадут в Рай.\u003c/strong\u003e\u003c/p\u003e\n\u003cp\u003e\u003cstrong\u003e14.   Этот хадис служит опровержением мурджитам, которые\nговорят, что совершать дела не нужно.\u003c/strong\u003e\u003c/p\u003e\n\u003cp\u003eЗдесь посланник Аллаха صلى الله عليه وسلم говорит Муазу не\nрассказывать этот хадис, потому что они оставят дела!\u003c/p\u003e\n\u003cp\u003e فَقُلْتُ: يَا رَسُولَ اللَّهِ أَفَلاَ أُبَشِّرُ بِهِ النَّاسَ؟ قَالَ: «لاَ تُبَشِّرْهُمْ، فَيَتَّكِلُوا» - Я\nсказал: «О, посланник Аллаха عزَّ و جلَّ! Можно я сообщу эту радостную весть\nлюдям?» Он сказал: «Не говори им (пока), а не то они понадеются на это\n(и оставят свои дела)».\u003c/p\u003e\n\u003cp\u003eВидите, в этом хадисе говорится, что «لاَ إِلَهَ إِلاَّ اللَّهُ» - это\nспасение, но даже этого не говори, иначе люди оставят дела, значит дела\n- это очень важно!\u003c/p\u003e\n\u003cp\u003e\u003cstrong\u003e15.   Этот хадис служит опровержением хавариджам, которые\nговорят, что, если человек совершил грех, то его «لاَ إِلَهَ إِلاَّ اللَّهُ» не\nдействительно и пользы не принесёт, и он становится кяфиром и навечно\nпопадает в Ад. Здесь чётко написано, что если у человека есть таухид, то\nон обязательно попадёт в Рай.\u003c/strong\u003e\u003c/p\u003e\n",
    "audio": "/audio/islam_kamil/part_3/109.mp3",
    "references": [
        "/islam_kamil_hadiths/part_3/35"
    ]
}
