{
    "id": "a9b246d8-8377-418e-a656-950e89486874",
    "index": 90014,
    "dir_index": 14,
    "date": "2025-01-14",
    "title": "АльхамдулиЛляхи Роббуль ‘аламин اَلْحَـمْدُ لِلّـٰهِ رَبِّ الْعَالَمِيْنَ",
    "text": "/text/islam_kamil/part_1/14.md",
    "body": "\u003cp\u003e\u003cstrong\u003eАльхамдулиЛляхи Роббуль ‘аламин اَلْحَـمْدُ لِلّـٰهِ رَبِّ الْعَالَمِيْنَ -\nКаждое великое качество принадлежит Аллаху, Который является Господом\nмиров.\u003c/strong\u003e\u003c/p\u003e\n",
    "audio": "/audio/islam_kamil/part_1/14.mp3",
    "video": "https://youtube.com/watch?v=WjIRjhdUeV0"
}
