{
    "id": "f6d5548e-cdcf-4b3b-9e3f-db9db8a26629",
    "index": 90049,
    "dir_index": 49,
    "date": "2025-01-30",
    "title": "Вера в Писания Аллаха الإيمان بكتب الله",
    "text": "/text/islam_kamil/part_1/49.md",
    "body": "\u003cp\u003e\u003cstrong\u003eВера в Писания Аллаха الإيمان بكتب الله - быть убежденным в\nто, что Аллах ниспослал Свои Писания.\u003c/strong\u003e\u003c/p\u003e\n\u003cp\u003eНапример, Мусе ﷺ Аллах عزوجل даровал Таурат, ‘Исеﷺ Аллах عزوجل\nдаровал Инджиль, Дауду ﷺ - Забур.\u003c/p\u003e\n\u003cp\u003eИ последним писанием является Куръан, который Аллах عزوجل даровал\nМухаммаду ﷺ.\u003c/p\u003e\n",
    "audio": "/audio/islam_kamil/part_1/49.mp3",
    "video": "https://youtube.com/watch?v=0oCIJ9thCJk"
}
