{
    "id": "ed93b849-63ed-4326-8942-e87f629a945a",
    "index": 101160,
    "dir_index": 160,
    "date": "2021-10-25",
    "title": "Можно ли что-то кроме откровения назвать религией?",
    "body": "\u003cp\u003eКак мы сказали, ислам ниспослан свыше и это означает, что его\nструктура – это Уахийю, Откровение. Ислам - это религия, и никто не\nимеет права причислить что-либо к религии, кроме Аллаха عزّ وجلّ.\u003c/p\u003e\n\u003cp\u003eКогда посланник Аллаха назначил что-либо халялем или харамом, то, на\nсамом деле, он делал это по велению Аллаха عزّ وجلّ, сам Мухаммад ﷺ не\nимел права изменять религию!\u003c/p\u003e\n\u003cp\u003e\u003cstrong\u003eВсё, что Аллах назначал в религии, это делалось посредством\nОткровения.\u003c/strong\u003e\u003c/p\u003e\n\u003cp\u003eАллах عزّ وجلّ в Куръане говорит:\u003c/p\u003e\n\u003cblockquote\u003e\n\u003cblockquote\u003e\n\u003cp\u003eوَمَا یَنطِقُ عَنِ ٱلۡهَوَىٰۤ * إِنۡ هُوَ إِلَّا وَحۡیࣱ یُوحَىٰ\u003c/p\u003e\n\u003ch6 id=\"سورة-النجم-آية-٣-٤\"\u003eسورة النجم، آية ٣-٤\u003c/h6\u003e\n\u003c/blockquote\u003e\n\u003cblockquote\u003e\n\u003cp\u003e\"Он (Пророк) не говорит по прихоти. Это - всего лишь откровение,\nкоторое внушается\"\u003c/p\u003e\n\u003ch6 id=\"сура-ан-наджм-аяты-3-4\"\u003eСура «ан-Наджм», аяты 3-4\u003c/h6\u003e\n\u003c/blockquote\u003e\n\u003ctable\u003e\n\u003ctbody\u003e\n\u003ctr class=\"odd\"\u003e\n\u003ctd style=\"text-align: right;\"\u003eوَمَا یَنطِقُ\u003c/td\u003e\n\u003ctd style=\"text-align: left;\"\u003eНе говорит\u003c/td\u003e\n\u003c/tr\u003e\n\u003ctr class=\"even\"\u003e\n\u003ctd style=\"text-align: right;\"\u003eعَنِ ٱلۡهَوَىٰۤ\u003c/td\u003e\n\u003ctd style=\"text-align: left;\"\u003eпо своему желанию\u003c/td\u003e\n\u003c/tr\u003e\n\u003ctr class=\"odd\"\u003e\n\u003ctd style=\"text-align: right;\"\u003eإِنۡ هُوَ إِلَّا\u003c/td\u003e\n\u003ctd style=\"text-align: left;\"\u003eЭто лишь\u003c/td\u003e\n\u003c/tr\u003e\n\u003ctr class=\"even\"\u003e\n\u003ctd style=\"text-align: right;\"\u003eوَحۡیࣱ یُوحَىٰ\u003c/td\u003e\n\u003ctd style=\"text-align: left;\"\u003eоткровение, которое ниспосылается\u003c/td\u003e\n\u003c/tr\u003e\n\u003c/tbody\u003e\n\u003c/table\u003e\n\u003c/blockquote\u003e\n\u003cp\u003eЕсли у Мухаммада, посланника Аллаха ﷺ нет таких полномочий, чтобы\nназначать что-то в религии, и это дело только Аллаха, то становится\nясно, что религия – это Уахийю, это только ниспосланные Куръан и Сунна,\nи тем более, \u003cstrong\u003eникакой имам, слова учёного, иджтихад религией\nстать не могут!\u003c/strong\u003e\u003c/p\u003e\n\u003ch3 id=\"если-религия-ниспослана-то-её-на-этой-земле-создать-нельзя\"\u003eЕсли\nрелигия ниспослана, то её на этой Земле создать нельзя!\u003c/h3\u003e\n\u003cp\u003eАллах عزّ وجلّ в Куръане говорит:\u003c/p\u003e\n\u003cblockquote\u003e\n\u003cblockquote\u003e\n\u003cp\u003eقُلۡ مَا كُنتُ بِدۡعࣰا مِّنَ ٱلرُّسُلِ وَمَاۤ أَدۡرِی مَا یُفۡعَلُ بِی وَلَا بِكُمۡ إِنۡ أَتَّبِعُ إِلَّا مَا\nیُوحَىٰۤ إِلَیَّ وَمَاۤ أَنَا۠ إِلَّا نَذِیرࣱ مُّبِینࣱ\u003c/p\u003e\n\u003ch6 id=\"سورة-الأحقاف-آية-٩\"\u003eسورة الأحقاف، آية ٩\u003c/h6\u003e\n\u003c/blockquote\u003e\n\u003cblockquote\u003e\n\u003cp\u003eСкажи: я не первый из посланников/и до меня были посланники, и я не\nзнаю, что ждёт меня (от Аллаха) или вас, я лишь следую тому, что мне\nвнушается/Откровению. Я всего лишь предупреждающий увещеватель.\u003c/p\u003e\n\u003ch6 id=\"сура-аль-ахкяф-аят-9\"\u003eСура «Аль-Ахкяф», аят 9\u003c/h6\u003e\n\u003c/blockquote\u003e\n\u003c/blockquote\u003e\n\u003cblockquote\u003e\n\u003ctable\u003e\n\u003ctbody\u003e\n\u003ctr class=\"odd\"\u003e\n\u003ctd style=\"text-align: right;\"\u003eقُلۡ مَا كُنتُ بِدۡعࣰا مِّنَ ٱلرُّسُلِ\u003c/td\u003e\n\u003ctd style=\"text-align: left;\"\u003eСкажи: я не первый из посланников/и до\nменя были посланники\u003c/td\u003e\n\u003c/tr\u003e\n\u003ctr class=\"even\"\u003e\n\u003ctd style=\"text-align: right;\"\u003eوَمَاۤ أَدۡرِی مَا یُفۡعَلُ بِی وَلَا بِكُمۡ\u003c/td\u003e\n\u003ctd style=\"text-align: left;\"\u003eи я не знаю, что ждёт меня (от Аллаха) или\nвас\u003c/td\u003e\n\u003c/tr\u003e\n\u003ctr class=\"odd\"\u003e\n\u003ctd style=\"text-align: right;\"\u003eإِنۡ أَتَّبِعُ إِلَّا مَا یُوحَىٰۤ إِلَیَّ\u003c/td\u003e\n\u003ctd style=\"text-align: left;\"\u003eя лишь следую тому, что мне\nвнушается/Откровению\u003c/td\u003e\n\u003c/tr\u003e\n\u003ctr class=\"even\"\u003e\n\u003ctd style=\"text-align: right;\"\u003eوَمَاۤ أَنَا۠ إِلَّا نَذِیرࣱ مُّبِینࣱ\u003c/td\u003e\n\u003ctd style=\"text-align: left;\"\u003eЯ всего лишь предупреждающий\nувещеватель\u003c/td\u003e\n\u003c/tr\u003e\n\u003c/tbody\u003e\n\u003c/table\u003e\n\u003c/blockquote\u003e\n\u003cp\u003e\u003cstrong\u003eРелигия – это следование («иттибаъ» إتِّباعٌ )\u003c/strong\u003e, религию\nсоставляет только Уахийю, и эту религию сохраняет Аллах عزّ وجلّ в облике\nКуръана и Сунны.\u003c/p\u003e\n\u003cp\u003eАллах عزّ وجلّ в Куръане говорит:\u003c/p\u003e\n\u003cblockquote\u003e\n\u003cblockquote\u003e\n\u003cp\u003eٱتَّبِعُوا۟ مَاۤ أُنزِلَ إِلَیۡكُم مِّن رَّبِّكُمۡ وَلَا تَتَّبِعُوا۟ مِن دُونِهِۦۤ أَوۡلِیَاۤءَ قَلِیلࣰا مَّا\nتَذَكَّرُونَ\u003c/p\u003e\n\u003ch6 id=\"سورة-الأعراف-آية-٣\"\u003eسورة الأعراف، آية ٣\u003c/h6\u003e\n\u003c/blockquote\u003e\n\u003cblockquote\u003e\n\u003cp\u003eСледуйте тому, что вам ниспослано от вашего Господа, и не следуйте\nиным покровителям. Мало вы поминаете!\u003c/p\u003e\n\u003ch6 id=\"сура-аль-аъраф-аят-3\"\u003eСура «Аль-Аъраф», аят 3\u003c/h6\u003e\n\u003c/blockquote\u003e\n\u003ctable\u003e\n\u003ctbody\u003e\n\u003ctr class=\"odd\"\u003e\n\u003ctd style=\"text-align: right;\"\u003eٱتَّبِعُوا۟ مَاۤ أُنزِلَ إِلَیۡكُم مِّن رَّبِّكُمۡ\u003c/td\u003e\n\u003ctd style=\"text-align: left;\"\u003eСледуйте тому, что вам ниспослано от\nвашего Господа\u003c/td\u003e\n\u003c/tr\u003e\n\u003ctr class=\"even\"\u003e\n\u003ctd style=\"text-align: right;\"\u003eوَلَا تَتَّبِعُوا۟ مِن دُونِهِۦۤ أَوۡلِیَاۤءَ\u003c/td\u003e\n\u003ctd style=\"text-align: left;\"\u003eи не следуйте иным покровителям\u003c/td\u003e\n\u003c/tr\u003e\n\u003ctr class=\"odd\"\u003e\n\u003ctd style=\"text-align: right;\"\u003eقَلِیلࣰا مَّا تَذَكَّرُونَ\u003c/td\u003e\n\u003ctd style=\"text-align: left;\"\u003eМало вы поминаете!\u003c/td\u003e\n\u003c/tr\u003e\n\u003c/tbody\u003e\n\u003c/table\u003e\n\u003c/blockquote\u003e\n\u003cp\u003eЗдесь сказано \u003cstrong\u003e«тому, что вам ниспослано»,\u003c/strong\u003e а это\nКуръан и Сунна.\u003c/p\u003e\n\u003cp\u003eИ в хадисе сказано, что посланник Аллаха ﷺ сказал:\u003c/p\u003e\n\u003cblockquote\u003e\n\u003cblockquote\u003e\n\u003cp\u003eقَالَ رَسُولُ اللَّهِ صَلَّى اللهُ عَلَيْهِ وَسَلَّمَ: « أَلَا إِنِّي أُوتِيتُ الْكِتَابَ وَمِثْلَهُ مَعَهُ\n«\u003c/p\u003e\n\u003ch6 id=\"مسند-أحمد-١٦٧٢٢-سنن-أبي-داود-٤٦٠٤\"\u003eمسند أحمد ١٦٧٢٢، سنن أبي داود\n٤٦٠٤\u003c/h6\u003e\n\u003c/blockquote\u003e\n\u003cblockquote\u003e\n\u003cp\u003eПосланник Аллаха ﷺ сказал: «Знайте, что Аллах Даровал мне Книгу, а\nтакже ещё нечто, подобное ей».\u003c/p\u003e\n\u003ch6\nid=\"муснад-ахмад-бин-ханбаль-16722-сунан-абу-давуд-4604-хадис---сахих\"\u003e«Муснад»\nАхмад бин Ханбаль, 16722; «Сунан» Абу Давуд, 4604. Хадис - сахих.\u003c/h6\u003e\n\u003c/blockquote\u003e\n\u003ctable\u003e\n\u003ctbody\u003e\n\u003ctr class=\"odd\"\u003e\n\u003ctd style=\"text-align: right;\"\u003eأَلَا إِنِّي أُوتِيتُ الْكِتَابَ\u003c/td\u003e\n\u003ctd style=\"text-align: left;\"\u003eЗнайте, что Аллах Даровал мне Книгу\u003c/td\u003e\n\u003c/tr\u003e\n\u003ctr class=\"even\"\u003e\n\u003ctd style=\"text-align: right;\"\u003eوَمِثْلَهُ مَعَهُ\u003c/td\u003e\n\u003ctd style=\"text-align: left;\"\u003eа также ещё нечто, подобное ей\u003c/td\u003e\n\u003c/tr\u003e\n\u003c/tbody\u003e\n\u003c/table\u003e\n\u003c/blockquote\u003e\n\u003cp\u003eЭтот хадис говорит о том, что ислам составляют только две вещи:\n\u003cstrong\u003eКуръан и Сунна, и третьего нет\u003c/strong\u003e. Что же касается таких\nпонятий, как иджмаъ, кыяс, урф, языковое использование, перевод, ташрих\nили тафсир, то это не религия, а её объяснение.\u003c/p\u003e\n\u003cp\u003eНикто не отрицает кыяс, идьжмаъ, объяснения учёных, всё это нужно, но\nвсему соответствует своё место, и это не сама религия, и,\n\u003cstrong\u003eследовательно, не может служить основанием или доводом для\nрелигии.\u003c/strong\u003e\u003c/p\u003e\n\u003cp\u003eСам человек не может правильно понять Куръан и Сунну, иначе он\nнепременно попадёт в заблуждение, ему обязательно нужно учиться у\nкакого-нибудь учителя. Все великие учёные – имам Аль Бухари, имам\nМуслим, имам Аш-Шафии, имам Ат-Тирмизи, имам Абу Дауд, имам Ан-Насаи и\nмногие другие, кто жили до них и после них, наши учителя, но и их слова\nне могут стать худжа, доводом для религии. Что бы они не называли\nхарамом, то харамом это не станет, имам может быть прав, а может\nошибаться; пока он не приведёт явный довод из Откровения.\u003c/p\u003e\n\u003cp\u003e\u003cstrong\u003eЧастая ошибка - когда принимают мнение учёного или его выводы\nза доводы для религии и считают религией не только Куръан и Сунну, а ещё\nи идьжмаъ и кыяс. Это ошибка!\u003c/strong\u003e\u003c/p\u003e\n\u003cp\u003eСлова имама – это ташрих, объяснение, и оно может быть правильным или\nже ошибочным. Правильно то, что иджмаъ нужно принимать, но нужно знать,\nчто не бывает такого иджмаъ, которое не основывалось бы в своих выводах\nна Куръане и Сунне, обязательно! Пусть те, которые отстаивают свою\nпозицию считать основанием и доводом для религии идьжмаъ, покажут нам\nхоть один случай, когда иджмаъ не опиралось на Куръан и Сунну, такого не\nбывает!\u003c/p\u003e\n\u003cp\u003eНапример, есть иджмаъ в том, что пять салятов в течение суток\nобязательно и об этом говорит Куръан и Сунна. Есть идьжмаъ о том, что\nсвинина и употребление спиртного - это харам и это также подтверждено\nКуръаном и Сунной.\u003c/p\u003e\n\u003cp\u003eПоэтому нужно знать, что раз Довольство Аллаха عزّ وجلّ можно получить\nтолько через ислам, нужно строго придерживаться его основ, структуры, а\nэто только две вещи: Куръан и Сунна. Следуя чему бы то ни было, что не\nподтверждают Куръан или Сунна, невозможно добиться Довольства Аллаха عزّ\nوجلّ: шиизм, суфизм, таклид или нововведения не приведут человека к\nжелаемому результату!\u003c/p\u003e\n",
    "audio": "/audio/islam_kamil/part_2/160.mp3"
}
